digestvid/__init__.py
digestvid/config_loader.py
digestvid/main.py
digestvid/utils.py
digestvid-0.2.1.dist-info/METADATA
digestvid-0.2.1.dist-info/WHEEL
digestvid-0.2.1.dist-info/entry_points.txt
digestvid-0.2.1.dist-info/top_level.txt
digestvid-0.2.1.dist-info/RECORD
