Metadata-Version: 2.1
Name: digestvid
Version: 0.2.1
Summary: A tool to transcribe and summarize video content.
Home-page: https://github.com/AI-Sherpa/digestvid
Author: AI Sherpa
Author-email: contact@ai-sherpa.com
License: MIT
Classifier: Programming Language :: Python :: 3
Classifier: License :: OSI Approved :: MIT License
Classifier: Operating System :: OS Independent
Requires-Python: >=3.6
Requires-Dist: moviepy >=1.0.0
Requires-Dist: openai-whisper >=2023117
Requires-Dist: openai >=1.0.0
Requires-Dist: yt-dlp >=2021.12.1
Requires-Dist: pyyaml >=6.0.0
